cqfd/__init__.py
cqfd/core.py
cqfd-1.11.dist-info/METADATA
cqfd-1.11.dist-info/WHEEL
cqfd-1.11.dist-info/top_level.txt
cqfd-1.11.dist-info/RECORD
