Metadata-Version: 2.1
Name: cqfd
Version: 1.11
Summary: cqfd is a tool to search skype account from a name
Home-page: http://github.com/megadose/cqfd
Author: megadose
Author-email: UNKNOWN
License: UNKNOWN
Platform: UNKNOWN
Classifier: Programming Language :: Python
Classifier: License :: OSI Approved :: GNU General Public License v3 (GPLv3)
Requires-Dist: argparse
Requires-Dist: fake-useragent
